Yolov4_KL_demo/__init__.py
Yolov4_KL_demo/loss.py
Yolov4_KL_demo/models.py
Yolov4_KL_demo/tool/__init__.py
Yolov4_KL_demo/tool/camera.py
Yolov4_KL_demo/tool/torch_utils.py
Yolov4_KL_demo/tool/utils.py
Yolov4_KL_demo/tool/yolo_layer.py
Yolov4_kl_demo-0.0.2.dist-info/LICENSE
Yolov4_kl_demo-0.0.2.dist-info/METADATA
Yolov4_kl_demo-0.0.2.dist-info/WHEEL
Yolov4_kl_demo-0.0.2.dist-info/top_level.txt
Yolov4_kl_demo-0.0.2.dist-info/RECORD
