Metadata-Version: 2.1
Name: Yolov4-kl-demo
Version: 0.0.2
Summary: Yolov4 with kl loss integrated
Home-page: UNKNOWN
Author: cleverhans
Author-email: xx@xx.com
License: UNKNOWN
Platform: UNKNOWN
Classifier: Programming Language :: Python :: 3
Classifier: License :: OSI Approved :: Apache Software License
Classifier: Operating System :: OS Independent
Requires-Python: >=3.6
Requires-Dist: torch (==1.6.0)
Requires-Dist: matplotlib
Requires-Dist: opencv-python
Requires-Dist: easydict
